csv_excel_matcher/__init__.py
csv_excel_matcher-1.6.dist-info/LICENSE
csv_excel_matcher-1.6.dist-info/METADATA
csv_excel_matcher-1.6.dist-info/WHEEL
csv_excel_matcher-1.6.dist-info/entry_points.txt
csv_excel_matcher-1.6.dist-info/top_level.txt
csv_excel_matcher-1.6.dist-info/RECORD
