Metadata-Version: 2.1
Name: csv_excel_matcher
Version: 1.6
Summary: Allows users to select and compare columns from two files (either CSV or Excel). The application matches records between the two selected columns and provides both matched and unmatched records, which can then be saved to an Excel file
License-File: LICENSE
